rfour
