Metadata-Version: 1.0
Name: rfour
Version: 0.0.3
Summary: RFour Request Response Protocol
Home-page: https://gitlab.com/vikingmakt/rfour
Author: Umgeher Torgersen
Author-email: me@umgeher.org
License: https://gitlab.com/vikingmakt/rfour/raw/master/LICENSE
Platform: UNKNOWN
